AST/Arrays.py
AST/BasicTypes.py
AST/Cast.py
AST/Controlflow.py
AST/Enum.py
AST/Func.py
AST/InitPackage.py
AST/Inline.py
AST/Lens.py
AST/Operator.py
AST/Struct.py
AST/Tuple.py
AST/Vars.py
AST/__init__.py
AST/node.py
TopCompiler/Alias.py
TopCompiler/Array.py
TopCompiler/CodegenJS.py
TopCompiler/Dict.py
TopCompiler/ElseExpr.py
TopCompiler/Enum.py
TopCompiler/Error.py
TopCompiler/ExprParser.py
TopCompiler/ExternParser.py
TopCompiler/FuncParser.py
TopCompiler/HindleyMilner.py
TopCompiler/IfExpr.py
TopCompiler/ImportParser.py
TopCompiler/Interface.py
TopCompiler/Lambda.py
TopCompiler/Lens.py
TopCompiler/Lexer.py
TopCompiler/MethodParser.py
TopCompiler/Module.py
TopCompiler/PackageParser.py
TopCompiler/ParseJson.py
TopCompiler/Parser.py
TopCompiler/RandomGen.py
TopCompiler/ResolveSymbols.py
TopCompiler/Scope.py
TopCompiler/String.py
TopCompiler/Struct.py
TopCompiler/TypeInference.py
TopCompiler/Types.py
TopCompiler/VarParser.py
TopCompiler/WhileExpr.py
TopCompiler/__init__.py
TopCompiler/jquery.js
TopCompiler/runtime.js
TopCompiler/runtime_node.js
TopCompiler/runtimebuild.py
TopCompiler/saveParser.py
TopCompiler/solve.py
TopCompiler/test.py
TopCompiler/topc.py
TopCompiler/terminal/__init__.py
TopCompiler/terminal/bundle.html
TopCompiler/terminal/gen.py
TopCompiler/terminal/terminal.css
TopCompiler/terminal/terminal.js
TopCompiler/terminal/test.html
TopCompiler-0.2.data/scripts/port
TopCompiler-0.2.data/scripts/port.py
TopCompiler-0.2.data/scripts/socketRepl.py
TopCompiler-0.2.data/scripts/topc
TopCompiler-0.2.data/scripts/topc.py
TopCompiler-0.2.data/scripts/topdev
TopCompiler-0.2.data/scripts/topdev.py
TopCompiler-0.2.data/scripts/topr
TopCompiler-0.2.data/scripts/topr.py
TopCompiler-0.2.dist-info/DESCRIPTION.rst
TopCompiler-0.2.dist-info/METADATA
TopCompiler-0.2.dist-info/RECORD
TopCompiler-0.2.dist-info/WHEEL
TopCompiler-0.2.dist-info/metadata.json
TopCompiler-0.2.dist-info/top_level.txt
optimization/BranchRemoving.py
optimization/Constansts.py
optimization/Escape.py
optimization/Inline.py
optimization/OptimizeInlining.py
optimization/RemoveUnusedFunc.py
optimization/RemoveUnusedVar.py
