Metadata-Version: 2.0
Name: TopCompiler
Version: 0.2
Summary: Compiler for Top programming language
Home-page: https://github.com/CodeClubLux/TopCompiler
Author: CompilerLuke
Author-email: lgoetz@islux.lu
License: MIT
Keywords: top top-lang compiler transpiler
Platform: UNKNOWN
Classifier: Development Status :: 3 - Alpha
Requires-Python: >=3
Requires-Dist: Flask
Requires-Dist: Flask-SocketIO
Requires-Dist: jsbeautifier
Requires-Dist: pypandoc
Requires-Dist: requests
